genai_bench/__init__.py
genai_bench/logging.py
genai_bench/protocol.py
genai_bench/py.typed
genai_bench/utils.py
genai_bench/version.py
genai_bench/analysis/__init__.py
genai_bench/analysis/excel_report.py
genai_bench/analysis/experiment_loader.py
genai_bench/analysis/flexible_plot_report.py
genai_bench/analysis/plot_config.py
genai_bench/analysis/plot_report.py
genai_bench/auth/__init__.py
genai_bench/auth/auth_provider.py
genai_bench/auth/factory.py
genai_bench/auth/model_auth_provider.py
genai_bench/auth/storage_auth_provider.py
genai_bench/auth/unified_factory.py
genai_bench/auth/aws/__init__.py
genai_bench/auth/aws/bedrock_auth.py
genai_bench/auth/aws/s3_auth.py
genai_bench/auth/azure/__init__.py
genai_bench/auth/azure/blob_auth.py
genai_bench/auth/azure/openai_auth.py
genai_bench/auth/gcp/__init__.py
genai_bench/auth/gcp/gcs_auth.py
genai_bench/auth/gcp/vertex_auth.py
genai_bench/auth/github/__init__.py
genai_bench/auth/github/github_auth.py
genai_bench/auth/oci/__init__.py
genai_bench/auth/oci/instance_principal.py
genai_bench/auth/oci/model_auth_adapter.py
genai_bench/auth/oci/obo_token.py
genai_bench/auth/oci/session.py
genai_bench/auth/oci/storage_auth_adapter.py
genai_bench/auth/oci/user_principal.py
genai_bench/auth/openai/__init__.py
genai_bench/auth/openai/auth.py
genai_bench/auth/openai/model_auth_adapter.py
genai_bench/cli/__init__.py
genai_bench/cli/cli.py
genai_bench/cli/option_groups.py
genai_bench/cli/report.py
genai_bench/cli/utils.py
genai_bench/cli/validation.py
genai_bench/data/__init__.py
genai_bench/data/config.py
genai_bench/data/sonnet.txt
genai_bench/data/sources.py
genai_bench/data/loaders/__init__.py
genai_bench/data/loaders/base.py
genai_bench/data/loaders/factory.py
genai_bench/data/loaders/image.py
genai_bench/data/loaders/text.py
genai_bench/distributed/__init__.py
genai_bench/distributed/runner.py
genai_bench/metrics/__init__.py
genai_bench/metrics/aggregated_metrics_collector.py
genai_bench/metrics/metrics.py
genai_bench-0.0.2.dist-info/METADATA
genai_bench-0.0.2.dist-info/WHEEL
genai_bench-0.0.2.dist-info/entry_points.txt
genai_bench-0.0.2.dist-info/licenses/LICENSE
genai_bench-0.0.2.dist-info/RECORD
