Metadata-Version: 2.4
Name: genai-bench
Version: 0.0.2
Summary: A powerful benchmark tool designed for comprehensive token-level performance evaluation of large language model (LLM) serving systems.
Author-email: Chang Su <chang.s.su@oracle.com>
License: MIT
License-File: LICENSE
Classifier: Development Status :: 4 - Beta
Classifier: Intended Audience :: Developers
Classifier: License :: OSI Approved :: MIT License
Classifier: Programming Language :: Python :: 3
Classifier: Programming Language :: Python :: 3.10
Classifier: Programming Language :: Python :: 3.11
Classifier: Programming Language :: Python :: 3.12
Classifier: Topic :: Software Development :: Libraries :: Python Modules
Classifier: Topic :: System :: Benchmark
Classifier: Typing :: Typed
Requires-Python: <3.13,>=3.10
Requires-Dist: click>=8.1.7
Requires-Dist: datasets>=3.1.0
Requires-Dist: gevent>=24.2.1
Requires-Dist: huggingface-hub>=0.20.0
Requires-Dist: locust<3.0.0,>=2.37.14
Requires-Dist: matplotlib<4.0.0,>=3.9.2
Requires-Dist: numpy>=1.26.4
Requires-Dist: oci>=2.150.1
Requires-Dist: openpyxl<4.0.0,>=3.1.5
Requires-Dist: pandas>=2.2.2
Requires-Dist: pillow<12.0.0,>=11.1.0
Requires-Dist: pydantic>=2.8.2
Requires-Dist: requests<3.0.0,>=2.32.3
Requires-Dist: rich>=13.8.0
Requires-Dist: tenacity<9.0.0,>=8.2.3
Requires-Dist: transformers<5.0.0,>=4.44.2
Provides-Extra: aws
Requires-Dist: boto3>=1.34.0; extra == 'aws'
Requires-Dist: botocore>=1.34.0; extra == 'aws'
Provides-Extra: azure
Requires-Dist: azure-identity>=1.15.0; extra == 'azure'
Requires-Dist: azure-storage-blob>=12.19.0; extra == 'azure'
Provides-Extra: dev
Requires-Dist: black<25.0.0,>=24.8.0; extra == 'dev'
Requires-Dist: isort<6.0.0,>=5.13.2; extra == 'dev'
Requires-Dist: mypy<2.0.0,>=1.11.1; extra == 'dev'
Requires-Dist: pre-commit<4.0.0,>=3.8.0; extra == 'dev'
Requires-Dist: pytest-cov<6.0.0,>=5.0.0; extra == 'dev'
Requires-Dist: pytest<9.0.0,>=8.3.2; extra == 'dev'
Requires-Dist: ruff<0.6.0,>=0.5.6; extra == 'dev'
Provides-Extra: docs
Requires-Dist: mike>=2.0.0; extra == 'docs'
Requires-Dist: mkdocs-material-extensions>=1.3.0; extra == 'docs'
Requires-Dist: mkdocs-material>=9.5.0; extra == 'docs'
Requires-Dist: mkdocs-minify-plugin>=0.8.0; extra == 'docs'
Requires-Dist: mkdocs>=1.5.3; extra == 'docs'
Requires-Dist: pymdown-extensions>=10.5; extra == 'docs'
Provides-Extra: gcp
Requires-Dist: google-auth>=2.25.0; extra == 'gcp'
Requires-Dist: google-cloud-storage>=2.13.0; extra == 'gcp'
Provides-Extra: multi-cloud
Requires-Dist: azure-identity>=1.15.0; extra == 'multi-cloud'
Requires-Dist: azure-storage-blob>=12.19.0; extra == 'multi-cloud'
Requires-Dist: boto3>=1.34.0; extra == 'multi-cloud'
Requires-Dist: botocore>=1.34.0; extra == 'multi-cloud'
Requires-Dist: google-auth>=2.25.0; extra == 'multi-cloud'
Requires-Dist: google-cloud-storage>=2.13.0; extra == 'multi-cloud'
